COPYING
README.rst
pyproject.toml
setup.py
microscope/__init__.py
microscope/_utils.py
microscope/abc.py
microscope/clients.py
microscope/device_server.py
microscope/devices.py
microscope/deviceserver.py
microscope/gui.py
microscope/win32.py
microscope.egg-info/PKG-INFO
microscope.egg-info/SOURCES.txt
microscope.egg-info/dependency_links.txt
microscope.egg-info/entry_points.txt
microscope.egg-info/requires.txt
microscope.egg-info/top_level.txt
microscope/_wrappers/BMC.py
microscope/_wrappers/__init__.py
microscope/_wrappers/asdk.py
microscope/_wrappers/dcamapi4.py
microscope/_wrappers/mirao52e.py
microscope/cameras/_SDK3.py
microscope/cameras/_SDK3Cam.py
microscope/cameras/__init__.py
microscope/cameras/andorsdk3.py
microscope/cameras/atmcd.py
microscope/cameras/hamamatsu.py
microscope/cameras/picamera.py
microscope/cameras/pvcam.py
microscope/cameras/ximea.py
microscope/controllers/__init__.py
microscope/controllers/asi.py
microscope/controllers/coolled.py
microscope/controllers/ludl.py
microscope/controllers/lumencor.py
microscope/controllers/prior.py
microscope/controllers/toptica.py
microscope/controllers/zaber.py
microscope/digitalio/__init__.py
microscope/digitalio/raspberrypi.py
microscope/filterwheels/__init__.py
microscope/filterwheels/aurox.py
microscope/filterwheels/thorlabs.py
microscope/lasers/__init__.py
microscope/lasers/cobolt.py
microscope/lasers/deepstar.py
microscope/lasers/obis.py
microscope/lasers/sapphire.py
microscope/lasers/toptica.py
microscope/lights/__init__.py
microscope/lights/cobolt.py
microscope/lights/deepstar.py
microscope/lights/obis.py
microscope/lights/sapphire.py
microscope/lights/toptica.py
microscope/mirror/__init__.py
microscope/mirror/alpao.py
microscope/mirror/bmc.py
microscope/mirror/mirao52e.py
microscope/simulators/__init__.py
microscope/simulators/stage_aware_camera.py
microscope/stages/__init__.py
microscope/stages/linkam.py
microscope/testsuite/__init__.py
microscope/testsuite/devices.py
microscope/testsuite/hardware.py
microscope/testsuite/mock_devices.py
microscope/testsuite/test_client.py
microscope/testsuite/test_device_server.py
microscope/testsuite/test_devices.py
microscope/testsuite/test_settings.py
