Metadata-Version: 2.1
Name: microscope
Version: 0.7.0
Summary: An interface for control of microscope devices.
Home-page: https://www.python-microscope.org
Download-URL: https://pypi.org/project/microscope/
Author: See homepage for a complete list of contributors
Author-email:  
License: GPL-3.0+
Project-URL: Documentation, https://www.python-microscope.org/doc/
Project-URL: Source, https://github.com/python-microscope/microscope
Project-URL: Release notes, https://www.python-microscope.org/doc/news.html
Project-URL: Tracker, https://github.com/python-microscope/microscope
Classifier: Intended Audience :: Science/Research
Classifier: Topic :: Scientific/Engineering
Classifier: License :: OSI Approved :: GNU General Public License v3 or later (GPLv3+)
Requires-Python: >=3.7
Provides-Extra: GUI
License-File: COPYING
